MANIFEST.in
README.md
requirements.txt
setup.cfg
setup.py
Qactuar.egg-info/PKG-INFO
Qactuar.egg-info/SOURCES.txt
Qactuar.egg-info/dependency_links.txt
Qactuar.egg-info/entry_points.txt
Qactuar.egg-info/requires.txt
Qactuar.egg-info/top_level.txt
qactuar/__init__.py
qactuar/__main__.py
qactuar/__version__.py
qactuar/child_process.py
qactuar/config.py
qactuar/exceptions.py
qactuar/handlers.py
qactuar/header.py
qactuar/logs.py
qactuar/models.py
qactuar/request.py
qactuar/response.py
qactuar/server.py
qactuar/util.py
tests/__init__.py
tests/basic_asgi_app.py
tests/client.py
tests/tonberry_app.py
tests/tornado_app.py