Metadata-Version: 2.1
Name: Qactuar
Version: 0.1.0
Summary: ASGI compliant web server
Home-page: https://github.com/Ayehavgunne/Qactuar/
Author: Anthony Post
Author-email: postanthony3000@gmail.com
License: MIT License
Platform: UNKNOWN
Requires-Python: >=3.7
Provides-Extra: dev
